{"1":["𠃍","乙","𠃉","𠃊","一","𠃎","𠃑","𬼂","丶","乚","亅","乀","丿","𠄌","丨","𠃌","𠃋","𡿨","乛","乁"],"0":["㇈","㇣","㇒","⺗","⺈","⺊","㇖","㇗","⺝","⺼","⺌","㇋","⺕","","ユ","㇅","㇇","㇀","㇉","⺄","㇏","コ","㇝","㇂","⺂","⿽","⺀","⺆","⺶","⺻","㇄","㇕","く","㇑","㇐","㇎"],"2":["巜","刀","亻","𠤬","𠙴","冫","𠤎","𪜊","𠆢","𠄏","七","丅","丩","九","十","丆","儿","𰆊","丁","阝","丂","刁","入","匸","𠀀","𰀫","𠘧","𠄎","了","𠄠","𠂇","𠄐","𠂆","匚","冖","𬺰","廴","𠄟","卩","几","𠃏","𠘨","𰍧","𠂉","𠀁","冂","乃","刂","厂","𰛄","讠","二","𬼀","𠂊","𠂈","龴","八","𰀪","𰍨","丄","勹","力","人","𫠠","𠁡","乄","亠","又","匕","卜","乂","𠄍","厶","凵","乜","㐅","丷"],"3":["门","𬼽","𰀠","与","𠃒","亽","𭠍","𰀰","亾","丫","𠂋","夨","𠓛","𰀃","䒑","亐","工","大","𡰣","亇","巾","勺","亏","夊","𠧒","𠀄","扌","下","土","亍","𬺱","丬","川","𡳾","𰛅","𠃓","龵","凡","万","丸","𭕄","𰀄","𠆣","𢎗","亿","也","及","孑","𬼸","𠙵","𬼖","亡","𪜀","乊","乆","纟","兦","𡯂","卪","彳","䶹","㔿","饣","𠚤","𠃔","𫜹","𠔼","夕","已","𠆥","𫡃","女","飞","𪟨","小","𰃦","孓","𠫔","口","千","于","乞","犭","乇","艹","𫝄","三","屮","㔾","丈","么","巛","弓","尸","𫝀","寸","叉","廾","氵","个","兀","𠔀","尢","凢","才","𡤼","卄","夂","丌","彑","孒","之","𠫓","上","𬺳","𰀂","广","𡕒","𠂎","士","弋","𠀃","囗","己","卂","干","彐","彡","𰀁","𢎘","𠀆","巳","𱍸","乡","宀","久","刄","𭅲","义","亼","山","㐄","刃","𠠲","马","习","幺","辶","忄","𫡏","𠂌","𡭔","卫","子","𣱱","𫶧"],"4":["孔","灬","仁","㕚","风","𠫘","匂","气","𢆯","牙","刈","歹","瓦","中","𣁬","巨","𠁾","勻","爫","长","𭅠","尹","𣱲","片","仒","夫","𡈽","刅","五","𭺫","毛","弔","𡈼","厹","𠃜","礻","心","𠥻","㞢","什","兮","爻","冈","収","内","文","𣫬","双","円","夭","𠀌","巿","𬽢","化","𡗒","𠆧","乌","𥘅","区","毌","𠔾","龶","支","𬼆","𠨬","𠕀","𢎜","尤","𠠵","肀","止","𤣩","𱼀","尐","仄","𠘭","𱤻","㓀","𡗜","丑","朩","计","尺","勿","尣","𡗓","乏","卝","𠮚","勾","攵","𠨐","𱐩","丏","𭃂","丰","屲","匀","仌","氏","𭂫","云","仍","厷","𢆰","凤","𠀉","太","兂","㸦","户","匁","圡","𰁒","队","凶","斤","𠤭","𠔿","屯","切","耂","𬺹","卅","𣱳","冘","互","𣦶","𠆦","丮","亖","𫡅","牜","𠔽","㠪","升","乣","𡴯","弌","仓","𠬚","币","反","𰀆","壬","今","內","𠙷","冃","𠤏","𠫗","𠔁","卍","父","开","手","介","𠓝","丐","𭅄","㝉","𰀡","见","巴","𰋵","仆","水","卞","勼","𠮛","𤓯","𣥂","𠚫","火","𢎟","𠔄","𠃛","罓","天","𡭕","厅","扎","㕛","丹","𠬛","专","㐊","𭃄","卬","㓁","毋","不","𭀘","卆","𫩏","𤓰","邓","幻","以","𠬝","𤣥","㐋","𠬜","勽","方","仏","为","𭄞","𠔃","仂","𠃙","犬","𫧇","𠁣","𧘇","𲋄","阞","夃","仑","冇","仃","斗","木","韦","办","亓","戈","夬","𪟽","𣎳","公","午","匹","六","㔫","爪","㕕","从","车","弖","𠨎","仇","戶","亣","𣬛","𭁟","王","艺","廿","殳","𠀈","井","𠓜","𠀋","月","𡿧","𰅭","𠘯","历","书","亢","𠘬","允","比","𢀳","𠬞","𠀇","予","丯","厃","𭣔","𰍰","𣂑","少","牛","禸","友","曰","𬺷","𠂑","帀","𣦵","𠠴","𣎴","冗","无","分","攴","厸","𭂩","厄","冄","仅","欠","𠙸","𠚪","仉","日","旡","𠬠","𠂒","戸","龰","𫜵","贝","卐","引","爿","元","仐"],"5":["𤮺","𠮨","𢖱","𪠲","𤴓","𠮧","令","仚","本","冚","仧","尓","仛","节","凹","匜","朮","𡆦","庁","戊","夲","𠀐","孕","叴","𭍺","𠂘","加","丙","叨","𮎛","宁","甲","央","𡰥","扒","目","句","亗","术","尔","穴","𭒹","𠕅","𰋙","㐌","且","𭙏","汁","屵","𪞖","只","冋","𠀗","𭑨","卯","古","甘","轧","𬺻","旧","㲺","氷","夗","𢒂","𠀍","𠙼","𠘲","𠕸","叵","㐱","𠬤","𫵳","弍","龱","𢀵","邛","𫨂","仨","厇","龷","𫲡","凥","𫑗","司","𠑷","𡰤","戹","𢆲","𠂔","匛","用","台","𠂛","伋","未","㒰","它","𤯓","弗","辺","㘝","对","凧","龸","𢀖","艻","𡉄","㞧","玄","𦫳","凷","𫵱","𠂟","𠮦","训","𨈐","𤴔","仔","生","𡭗","𡖅","龙","𡗗","𠀕","禾","𫢉","𢖫","𦘒","𢖭","𬼈","归","业","𣱽","𪜠","氐","戉","𠆩","𡯄","丗","𣄼","𠕄","𫩑","另","𦫵","母","宄","𠕁","仙","平","𢎨","代","宂","𣎶","冊","尻","𡗛","厈","𡯊","𱑱","丕","𪵨","𣎷","𦉭","𠮣","布","𪩲","囙","叶","示","𫵲","𢌮","𨑏","东","囘","卢","立","㞤","夘","𠂝","㠯","失","匇","𠫝","𡆤","由","𰰝","凸","写","丱","廵","刍","氿","斥","乎","奶","右","礼","𠥽","㓛","卉","𦓐","𫜸","𰉗","𡳿","市","𠮥","汇","𫞕","𠮢","広","石","边","正","𰍩","仕","𣱷","民","𠦀","罒","阤","𠆫","氺","𠣏","𱎛","𩰋","务","𭺛","艽","処","戋","叐","𦉫","𠃢","歺","𠘳","矢","号","召","丼","𠙹","㐍","𭤟","弁","𠂞","𠆳","庂","𱏿","㲹","𩰊","㐀","氾","㐲","圥","尒","𢆉","𥝌","肊","卌","𭁳","𡥂","𰀢","丘","𠂡","𡯇","𡴴","付","冎","皿","申","㕥","玉","夯","㕣","叱","𠙻","击","払","𢦍","功","乐","包","𠂀","叧","处","主","甴","𤕫","占","𰀈","邜","冭","𫧀","巧","北","𠁤","永","册","旦","𠀔","乍","札","帅","瓜","丝","厺","田","𣱵","𪢱","𰃮","𮍌","刊","冬","𱘦","仢","𡔛","𦍍","世","钅","𠕶","仞","叏","𠕉","冉","艿","卡","电","讨","𠙺","㞋","汄","左","𦉰","叹","汉","犯","𢁓","疒","鸟","𠕷","仡","𠮠","白","四","𠂕","㓜","汀","𨙰","屳","𡚬","衤","屶","𠕵","厉","兰","闪","𠙽","㚢","兄","匝","丛","半","卭","叩","外","印","𠂠","𡉀","𡉁","仟","卮","屴","他","幼","甩","𣎵","犮","圤","𦉪","𰆰","艼","打","𠮡","厼","𭑧","𱍺","史","皮","𰀉","匃","奴","可","圧","𭀚","发","𭺜","𡥀","𠬢","𢌯","匆","灭","𭐝","𫠣","𭁠","仝","头","圣","冯","艾","𭼽","尼","出","末","𡰦","氹","去","㚈","𣱹","𡗚","仺","𠬦","叫","氶","疋","夰","癶","矛","囚","尕","𣱼","𠨯","𢎢","𣍝","必","夳","弘","𠀎"],"6":["灮","㠩","𡆫","𰌵","芊","伐","优","𠮮","𠤱","𠠼","地","阳","师","纣","𠄢","𢪀","𮎜","夻","夹","汗","𠂨","㐆","岀","𮓱","𭴁","𫠤","𢖶","𪫆","刕","𠫡","𠕎","兆","刎","㕂","𡵄","扣","㞪","危","𠯂","𠨿","𫝁","𣂒","𠃨","𪟩","伪","㡯","𡉓","𭸵","𡉐","𣦼","𡉖","阮","杀","阴","旨","会","𢆶","亘","尗","𠮯","艮","红","兴","𰁦","𣲇","汑","吐","众","𤕭","好","𫤫","亚","羽","曳","𪧷","庅","𠇏","𠮷","夙","犴","𦫷","甪","存","𨸀","闭","𠇍","㕄","厊","米","𪢶","𱛇","𢁟","圩","并","𠨺","𠀠","㬰","芅","𠮵","䏍","𠁦","𠕻","劦","𡵆","𡚱","毎","齐","农","𧰨","𡚯","吁","𪜌","汤","肋","衣","𥘈","𨚌","㚐","戍","㐼","夺","迁","汒","𱝼","𡦾","岂","夅","幵","机","州","䇂","𦓤","㞍","仼","色","𱐔","企","㚏","岁","毕","𠔉","页","叿","𭥌","𰏒","㓙","𠕋","纥","式","吕","仿","𤜭","𤯔","𠮰","则","𠂥","㐂","芓","㒲","𠮲","𪵩","帆","朶","𡖈","芑","犳","𡚺","覀","𭘑","㣼","𡰪","囝","𤰃","𢗀","㓝","关","级","𭷔","肌","似","𡕟","戌","𫇦","孖","尖","𡴀","决","𰋷","𡧄","爷","玑","牝","自","𱒃","汣","𰅱","芍","忈","芕","厌","舌","夵","吏","𡆬","朵","𠬪","刖","光","𰁜","约","伎","𭅰","伇","㔻","𰢴","𬐃","奸","列","𡖉","贞","伊","刚","旫","圪","祁","𡰮","血","至","𡚴","戏","𠯇","圯","共","𦍋","乑","宇","𣎽","圫","芆","𤆅","𢁝","孙","𬻻","𡿫","𭘒","𡔜","过","朿","𦫿","延","𫥞","𣏀","导","当","吊","𭆨","弛","早","𦣞","𠨾","汐","异","𠣓","𣅀","欢","夸","灰","𠇔","竹","𱐕","𢎱","𪥤","𫧏","庄","𦍌","𠑹","产","糹","芎","灳","牟","芒","𫡑","执","㚣","玎","吆","𠄣","𠦃","匈","吂","𡖇","𡦿","𤘖","丞","肎","耒","劣","汎","𠦅","𠖲","𠬩","襾","𡰫","虫","𭥎","𪤷","死","甶","收","任","而","㞬","负","迄","吒","汙","吋","如","㫐","芉","𡰱","尧","忙","迈","乒","向","𱏻","𡉑","丠","𡉊","𠀜","圭","邪","壮","年","𱒅","𦥓","尥","份","𠕽","両","𠕌","𠯃","问","𮦄","汋","圶","动","𡗝","朴","污","𦈢","𡵉","芋","守","阩","臼","𡗡","𢁙","𭨘","次","𬼉","字","㞌","邠","気","刘","𤰔","设","𨈑","𠕾","伩","𡵂","𨸢","𠂭","𠦍","凪","池","𭥍","𠘻","轨","此","𭇁","囟","阪","乔","𫝢","𠦏","𥝍","闯","妄","阥","夷","伢","那","杂","𡆩","巩","汲","𠃧","廷","𫭙","刑","𫥁","艸","朱","有","㫃","龹","㐁","𠫣","𠯄","仲","巟","𠮳","伝","兊","𠅇","𫾦","亙","奼","屾","臣","亦","邢","旬","𫡓","防","华","𣎼","𭑃","㞭","江","𱜢","𣁁","亥","舟","伏","𭃌","𭗼","因","𦥒","𬇗","团","汆","交","芝","𠤮","䏌","𤆆","汍","全","𬽪","在","扱","芏","丟","划","压","肉","𢀛","囡","戎","奻","岌","𠛄","𠂢","𬽄","𡥄","寺","网","𠀚","氽","𱄿","扛","𱤽","𬻀","𠯊","汏","𡕖","圳","丢","曲","𠦄","聿","𤆋","𠚾","同","名","𠅃","帇","回","托","穵","𪞘","𢨩","各","𭁆","汝","件","𠦂","𡴂","𪱙","尽","再","屰","𡗞","𢦏","凼","𢇛","𰆗","耳","休","𡵃","𢦑","𰅰","𢖻","合","𠂤","彶","迅","后","𠀘","忛","虍","汛","伙","冰","老","安","㱏","𢌰","舛","匡","宅","厽","缶","㐪","朽","𬔖","西","𪩣","圴","㓞","㓇","𭆙","𮕤","犱","𬻄","伒","𥫗","寻","伞","仰","癿","成","𪢴","尘","𡗢","争","军","㐫","许","多","冲","𭺽","𭍽","达","㕦","考","𤆌","羊","𠘺","𠫤","𨙺","𢑑","𡧊","𡆪","𠂬","𡰯","卋","𰃝","旭","𡯎","𢩭","邦","𦫼","百","𫰉","𧰧","先","𫠥","圮","匠","㲽","𠆸","𦥑","夶","凩","糸","𢌜","行","𡿪","芌","𣎾","𠧗","𫹭","叒","㜽","𡧇","吉","𣦺","𣎺","弎","𠇊","𪵪","䒔","吅","𢓁","充","𡿩","弜","𣲂","汜","佢","𫯜","𠂂","㢟","𰗑","兇","买","芃"],"7":["糺","吞","𬁟","𡵩","𠯚","𥁀","吴","𡗱","𢗝","𰆘","𭥐","戻","𥘑","𤼿","㓠","迎","甫","佞","夿","汞","𣲎","但","𰨛","𫨶","卤","呉","扳","𤬦","𠇽","𡥈","𠔍","𡇂","忮","廸","奂","𣏂","岛","库","杄","𡭝","佘","汰","沖","补","灵","𬍑","亜","作","君","𢪙","陁","寿","纽","㺯","𥃫","𦬅","𡵱","闷","㞎","伱","攼","𪞏","𡿯","岗","何","夋","𫲽","𠀧","𣅋","𰤲","㞷","𠖀","𫡆","𭮁","𫢑","𠇚","汾","𪜭","𪟙","邱","囤","肜","花","車","更","县","却","𢌺","𡿮","𭟯","邑","旵","妞","抛","庒","乱","扲","尨","㕯","间","𰆺","弅","𫯝","宋","𰹲","𦔮","刪","𡉰","困","呌","𲂺","𰍱","𦣝","𦉳","𱥺","扼","売","𰅴","批","沔","叓","㠻","坒","时","𱥯","皁","沛","妢","呀","𣅌","沄","𫠨","𦒱","冷","𪱳","辵","見","佊","陂","犹","䆑","𰿩","改","𠯳","兎","刜","洰","角","𫝣","玖","𨙨","𡕙","吿","沐","𡗬","𠯭","𥐘","劯","𨑦","吟","沃","沂","伿","近","𬉸","扮","𡉵","沅","𬻏","判","纯","块","㶣","芘","把","𧾷","劬","阻","忌","伹","杋","䖝","抈","𥃰","狃","𢁳","児","芮","里","弟","𠖸","坠","忸","𤰜","𰠧","园","孝","沉","𭣣","吽","孜","系","甸","𫔮","抄","𫲺","赤","𡵖","酉","𭕇","𡛊","汦","𠃬","𤰖","𱖐","含","㔷","听","𢓄","吠","㧍","阿","圼","𣲙","怀","坐","卵","忒","厏","𢗦","𡵫","皂","闰","𰎋","灾","杆","佉","冶","汨","𫩞","𭤔","宎","𦉬","𫹏","佐","扽","祀","㒷","𡧎","肑","𠩈","肙","𣏒","况","秀","𤆎","伯","投","扯","𢒈","汩","𢁺","良","囱","𠯍","忺","𫹍","𡉺","𫯞","𫠉","𬽲","报","呇","进","言","𫻨","灶","㫖","局","克","芪","皃","𭯺","𠛢","呄","闵","辰","巵","男","纺","𧺆","应","芚","纷","𢪒","宐","𨑲","丣","𫭠","𡵯","𤓳","吝","𢗡","𰰡","狄","苋","宍","𥝐","杜","每","杗","岜","帋","吹","沟","𠤕","𡔞","坔","𨑢","足","𪞐","矣","𤆍","杦","𡶀","𣧄","囧","𣏏","劭","匤","苏","佥","𡧐","𪜢","呙","㪯","弃","迏","𭕆","𪜱","芟","声","芙","𣏋","𱑲","𣏉","𠬸","𣏌","刧","𬎿","𡆾","𬉶","𠇾","𡉣","狂","壳","㳊","层","𮕜","𭛞","沒","𣌡","佋","芺","坊","戓","𠯑","𡰶","芰","𫲸","𠄘","𥃭","𢪫","究","你","𬋻","𥃩","𡥉","𠇮","条","𤆗","汭","𡆵","完","𢌳","𠇩","狇","汵","𰅲","彤","囯","𠖼","李","𠀤","呆","𰢵","𭃡","𬌪","囬","㒵","冝","村","芬","折","㝴","攸","𱱴","𢎿","杏","対","芾","𬇚","㳉","𭣢","肝","杨","禿","𠕒","宊","抉","附","芠","走","𡵧","忘","孛","𠦒","𪜬","𡗮","肖","㫗","𭆃","𠧚","𤰗","两","芹","㚓","芡","𪢾","呈","坚","杊","斈","曵","夾","囲","町","豆","𢦒","坎","囪","卲","坂","㤋","伶","位","芽","兵","汪","𠯪","𢎀","扸","芷","泛","巠","𰀾","𠯌","弄","坏","彣","㒴","初","芼","杖","吾","身","𫰑","束","灸","厎","𨈏","𠯓","𠑽","𥃦","阼","𪩡","迊","㚒","沚","庇","汶","邯","亨","肚","坑","𨸲","冏","岑","灼","医","𨑳","𱰥","杠","鸡","兑","旰","抗","汧","豸","忡","𦬊","呚","芫","抂","𱒋","秃","𢀜","妊","屁","佗","𠁧","㞱","陃","𠯫","𫩜","凬","㳂","宏","𥤤","扵","𡧍","妥","𥸦","㞵","戺","囦","体","𡉤","连","苂","𦉱","伽","启","𣲑","𫹯","尾","即","孚","𭚧","𡇆","夆","材","㳄","𦉴","𦬆","𫲷","忤","牡","贡","辛","𡗥","劫","甬","𭓟","利","芯","𦘴","𫔭","𠅋","坌","羌","𰌞","攻","𬽵","肘","串","𣅈","𣅍","𡗩","戼","妨","别","決","芭","𫩙","𥃮","𨑭","镸","芴","𠡉","坟","𠘽","𣅑","卣","围","𡉚","釆","災","没","劳","肓","㹞","汖","𭻾","芧","𦣻","𦘶","廹","𬂝","沈","旲","𡵶","𰤳","罕","𪪳","抑","𠰅","𠇗","杣","抇","𢇦","𡵳","呏","𥤥","㘮","𡉼","芣","㽗","佑","远","抌","𣅄","均","庈","肠","抓","𠛜","陀","㝑","𥐛","沙","坓","𠑿","𰍪","𢗭","丽","㫒","陈","䏎","形","𠑾","抖","𭣖","𠬲","𠩉","牢","𭮀","㱑","𨚪","役","龟","否","戒","圻","皀","员","兌","尫","圽","𣏈","序","灷","𥎦","杘","芸","佦","汱","𡴇","技","別","㦮","𱥻","妓","𦥔","扶","攺","兕","𠇤","还","𢗰","𡉿","吻","𠬶","㝐","私","芥","𡆴","抐","𤼦","努","呂","灻","𢗼","𢗑","尪","邵","妍","亩","张","茾","図","労","𡉸","𠇦","汸","𬜥","㫕","严","免","芿","芈","呑","𣅘","彷","谷","貝","佔","𨑮","岐","找","寽","壯","助","𠦑","闲","𪜮","𮞅","求","步","𡴆","沕","麦","妟","㐬","肟","𣲭","希","䀏","㧎","床","𰙜","𢨪","住","𭗾","𣲩","𰅳","社","𣍟","𥃯","𣅆","呎","沁","杓","盁","𢪘","𬷽","芳","芶","旱","匣","伸","肞","㝎","岙","𣥈","訁","纳","㒶","𫠩","𠩆","㽖","财","𬉹","来","刢","劲","迍","告","芩","佛","𫝹","𰠿","𭶻","余","伴","㤀","㣊","估","穷","犾","岕","𢗨","㿝","低","妙","𥤦","𭎃","吳","杉","尿","豕","苁","旳","𨚫","快","𨚡","巫","我","𧮫","𮎟","汫","乕","甹","𢪛","𡗶","志","忍","𢦙","𦬑","𣅔","𫝕"],"8":["㡀","歧","厔","奅","𤕰","拌","咼","𱼧","玧","刾","𡶓","爸","昍","玫","𢇳","𭅑","狐","𭑈","具","𦙟","侄","𦙑","卥","坡","杴","𥝝","昆","法","泠","炊","𫰗","𭺲","肬","臥","𭠂","岺","𠚍","备","廻","歨","肩","厓","𦬞","贤","秊","虱","𡇋","牧","㹨","𱐍","糾","竺","𫩣","官","弥","泙","㺳","𠦝","孥","欥","沫","廼","肥","苟","奇","𪰎","河","泄","坨","拘","𣥕","夌","苖","建","帛","呴","𠄭","𭕘","肰","𲀥","𠧢","版","𠰞","佻","𠈌","𢘤","㘠","拑","𭇎","㱚","坣","终","幷","苲","盱","杰","顶","𡱈","𭚫","泍","𠰛","𠄮","釒","沼","杳","斩","单","𨳇","㓤","金","妲","卑","隶","𨒒","拋","郁","弩","𡶟","㚗","明","宗","杯","典","東","𠰓","𡕢","𣏚","念","𡭧","贫","肿","盰","𢌿","刺","𣲲","𠦜","臤","𦍐","其","迡","䒤","治","郍","畀","枕","㕻","𧠆","函","怽","咖","顷","𣥐","青","泫","𣢊","彼","肶","𠛼","㦿","𥐧","呱","侙","质","𭁈","岝","劼","𱒒","昊","苳","𠈣","苶","周","佯","陏","𡊦","陌","𫇭","券","𧗠","𠙉","𥤱","𠩋","䏔","㐭","和","秅","沽","𨐌","𣂔","𰤔","迤","𫆀","𠈃","炒","𦬬","岩","姑","若","㣇","𦉼","图","忽","油","旹","受","𡶩","盂","怛","𠗆","枉","効","匋","𠧧","㚘","宓","帕","泅","𢨯","𩙿","𰮋","苙","昙","狍","泮","肃","者","忠","𤰞","𫩧","枣","齿","盲","拍","㤅","𭅺","沓","忞","𪯢","坸","昂","佳","𫩠","奉","𪰊","录","依","刮","担","坪","飠","非","𡿲","朋","臽","𨸏","玟","秉","䄪","𥄁","衬","泜","𥸨","姁","旺","卦","㓣","责","𭁴","㚔","𠀭","𢦟","呥","泈","卧","鼡","肴","枚","㤕","征","𦏲","舍","𣅳","𮝾","𠒋","抦","贯","𫨈","𱬷","叔","𭴉","𣅟","卺","𭴎","茐","𭣤","𤆦","𡱀","易","咅","沝","𡱂","𡶇","𭴋","拔","苑","黾","戽","𡊵","苾","𱡻","𠛫","昃","枒","实","岪","㐩","坥","衫","罔","𠜊","㤁","𰹈","戔","转","𡛩","茂","杼","𭒽","弧","垂","𤰠","𭟲","𱛖","屈","承","𦬪","咎","放","𢆻","㱛","𧈧","杲","采","苦","冐","𤤅","𦙃","𥤧","𡶦","鱼","𡘆","性","𭺳","𦒳","𫠭","𫧠","𢍀","参","𥃳","厒","肯","𫤘","佴","妾","㕁","郅","𮨶","叁","𪥌","旻","昗","降","迥","注","畂","𡴋","抺","㑒","𢼂","欣","闹","𠱀","𰁽","觅","昀","咒","𡊨","宜","㭊","𣏽","浅","侘","𭎇","刻","抨","岶","冞","坬","㸒","怡","沲","炆","押","𢂇","凭","欦","𡧟","𥩘","㔽","苘","𪠨","𠧦","尭","𠰕","㞺","㫄","卓","怐","昘","𢺸","忝","宙","𰗕","炬","𭟰","坩","味","𣅜","直","佰","苻","屇","姈","败","卹","𠈪","泥","𢼄","佫","岨","𪯱","戕","𦨉","䒚","呵","瓫","𤆬","宛","㶨","𠀬","岡","侎","妮","𭸾","𥎨","狗","届","𢍁","𤽇","拂","国","叀","苠","𬅟","忢","𡊮","𨹅","的","枋","𪟄","𠤻","𪻓","贪","邿","姆","𬂣","亝","𫐣","𥁃","杵","忥","𡘃","𨒙","虏","𧘗","审","𧈠","迭","𭑊","𭶪","𥝢","枀","𢨳","𪧈","卒","拐","𭩢","㦰","苛","𭥗","𤝗","房","怪","妹","𠛧","夜","玢","松","枈","𡇌","茀","变","抱","侫","𥘪","佸","㚿","秇","𪯲","並","茅","徂","泔","阜","䘚","𠈇","𧹘","侌","枢","𡊥","叕","苹","羋","𥘣","侍","𰥐","兔","斧","𫻩","𫯢","𢘆","𡿱","𰇑","𡊭","表","往","迱","𤘴","刷","画","述","英","学","净","𪰋","𬮠","𱽐","径","𣥜","㘳","氛","牀","沮","㚖","𠰥","𠒃","䒝","𦉾","苓","苕","始","㸓","奔","林","㔙","沬","尚","㢱","㧜","囷","穹","拉","泓","隹","門","籴","靑","𦓎","𡶤","虎","𱪮","茄","事","杪","𥃲","昇","𠈉","𣬅","昋","𭥒","𱣀","抳","沸","㘴","𭎌","茇","𢫕","畄","郎","忩","豖","抯","𮕦","𥃷","限","或","戾","苪","炉","板","𣏦","到","𱵼","𠫭","沱","𫂱","㚻","𤿌","怯","乳","㲎","侖","㳎","𢪿","昔","𠫯","帚","刹","枭","𠩓","𣐂","㕺","𪠁","妬","侠","旾","𬚳","𱖔","𪪎","杸","𣥖","杭","㞑","拙","炏","庚","㒺","茋","刵","𢏏","𣢐","定","怗","䀐","泡","享","㕞","匊","𥁄","牪","择","狛","𡬠","炗","郑","迦","𡧧","𤝡","㤐","𦬰","兩","𣥚","𥝕","析","冾","𪫩","爭","𬜦","诣","𡊱","屆","玨","妱","季","兖","侁","凮","斨","怕","炙","招","穸","𠈗","𡥚","果","𰏴","𠙇","㽵","苽","䏙","育","𠰣","𦙊","𦬣","丧","𨒣","𫵖","𦬦","茁","疌","苞","迢","𣧋","坮","𫼉","𤤋","披","弆","忿","糼","命","姄","𠒆","𧠇","府","𱻊","斉","泯","𡧢","軋","波","供","㞐","祅","昒","沷","兒","侈","況","𤓻","𦨈","怚","𣏰","孟","曶","𢒊","坫","茆","帙","㦲","𡊎","居","例","𡕥","拈","𰧭","岱","宖","苴","𪜹","武","苫","𧆛","㧝","𡧘","𢻻","甾","抽","徃","炎","𭥕","𣧌","宕","㸚","泣","兓","𤘆","㟀","苜","岢","𠧠","尙","矾","弦","宠","𡶣","舠","𤰅","知","𣏟","𡛼","委","𬇊","𥸩","侃","狀","沭","空","刲","𠈄","店","奋","牨","帖","𣏔","𱑎","取","制","𣐇","底","迫","歩","臾","迮","岸","枝","卷","肫","妸","𥝞","𧈟","𧈡","㝵","奄","舎","𠂳","肏","𤆯","䀑","䒥","𲂻","沾","𭁨","坤","规","刼","𡊚","帘","泪","耶","実","泊","𡭨","垃","陋","佩","坦","服","𦍎","毟","昑","𦉷","𠛱","欧","𰏤","秈","些","彔","昏","京","苨","𭥖","丳","𣐁","苔","𢇻","昌","䢸","炘","坴","昕","𥐦","庖","𬙘","宝","郊","亟","𦙌","𭔫","彿","䍐","𣥏","奌","罗","卖","𦙚","囶","奈","岳","𱞂","𡘊","泌","靣","𡊙","𪠆","𡇈","𢆎","固","劵","𬉻","泳","乖","侣","肺","岦","𫃚","苿","𫇩","所","斦","𭀡","股","瓮","𢂋","玪","𬎾","匼","𡱅","㚼","佶","物","岽","畁","𡱁","使","罙","𭎊","於","庙","匌","㕿","𪸓","㹜","𠱄","𱺵","𭭛","𢏈","玩","𭖒","㣘","長","𣏼","𭃚","𠣜","來","幸","孤","𭮃","迪","𠩕","炅","𭅉","苐","茌","𫾨","泃","㛁","𰥍","矤","昛","勆","炇","祋","侗","雨","妻","亞","苗","𥤨","拃","废","𢆍"],"12":["鲁","𦣦","絮","𣸁","欹","媞","窜","棠","蒌","𤔔","翔","䓨","缘","䘖","𠷰","𮊿","𥁰","𣁽","𡈂","𪿢","𰗷","琦","𡈉","韩","堶","硬","韌","隓","𬻨","筒","痗","楇","街","䓤","矞","㟯","𦜳","羡","𣔋","惑","期","舒","𧰷","𨕂","評","絙","渙","䟫","𨾜","阔","㱕","𠗲","厦","㪚","粤","湘","傅","湮","萼","稂","窘","𦱄","備","殽","椑","𣈆","𤊅","𡬵","湛","爲","晶","皓","𬌡","淵","葏","焴","惹","揂","𡬳","𮦆","畬","創","絡","馭","欻","葢","𦱧","嵗","順","奥","集","款","殼","堯","辜","㫺","𠥔","筋","𦱋","阑","㲃","𪩃","詠","渴","須","葱","雅","粦","甤","𰚢","廆","萷","董","翛","𤉷","啼","𢽬","敦","棗","筄","戠","覘","𢉲","䨿","揾","晱","𥿻","臸","𣸸","𭆏","辇","袲","㫿","蒐","焱","御","疏","㦸","㷅","堪","疎","棼","㜀","强","𣂪","戢","臰","嫂","痩","兟","𫟛","𦊽","喭","揚","湟","𥆝","翚","𤯦","𮕹","𤭐","湜","㪙","𢁅","揔","鈚","𥇇","寒","𣸈","䎜","𩾏","𡍸","貃","媛","答","愔","買","𣓕","啻","鉅","脽","間","媒","𬝘","絜","斌","觚","敬","握","臮","䇪","棄","豿","𡲤","渧","𰙫","焭","𠗱","琢","普","蛰","𠁊","傌","衆","紫","葅","厤","歮","尋","韮","耋","𨐓","葛","揉","裂","鄔","賀","貸","琶","塊","凿","𭆐","晻","悶","募","絲","焞","湏","辝","渻","鈞","琴","𢽟","惺","絕","酥","欼","棃","鼎","徥","貿","颉","掣","𮞬","𮫙","開","𢽹","喆","𣓪","聑","𭣺","脾","琼","厥","舜","葩","焣","蛮","散","䆤","䆥","赏","𬮴","貵","欿","黃","歯","森","𱂥","䭴","愄","琰","𭭎","𡲫","㮃","硠","甯","湄","𪠮","湼","棘","𨔶","𦲸","扉","雯","𤲆","逾","統","𭮶","插","遗","喃","圌","惸","𩇮","筑","𦲿","腱","慨","達","援","税","𮈍","𫻹","葭","徫","覚","温","𦱤","満","𥆞","筳","湡","𭪴","𮥷","𤊙","湅","𪿟","棱","𡬶","遅","㴠","𱽷","幾","𮙺","𥥽","笿","堹","晷","𪧺","硯","窙","曾","䊆","𢽠","琵","閏","䓬","筌","喂","徧","渫","閒","棓","景","脹","喉","蜑","湯","䑬","結","量","訴","湌","𧊒","㻚","牌","猥","揸","葳","遁","悹","叅","尊","然","軬","𣈅","越","赑","琳","稊","嵒","嗟","滞","矟","𠥓","𭈹","𮗁","裁","渡","舃","媚","凱","稅","𰷣","𣄃","㮈","鈙","葻","違","㝹","琮","𰭢","𩂊","賁","程","䧘","絭","猋","竦","犇","𠢋","萹","遇","煑","䠶","盜","游","趁","欺","番","𬀉","𡙗","煮","詔","㞚","葃","軲","痛","𰕎","𬈆","𥬬","䂓","雲","童","湳","犍","愧","髠","𰨚","殘","㰳","𣓏","遂","𡍮","遍","䜭","㑴","䐌","淼","喑","稈","戟","萺","𦱽","遄","㷊","𪧘","𦧗","𡩋","𤗊","喦","揭","𫏵","粟","提","滑","喟","棒","單","勞","𧦴","勝","葺","𭴺","𱗐","𥚢","腊","飲","裒","蜓","𧚍","貴","𡩖","窖","𫤝","犀","閔","㢏","棟","惰","衖","馮","棸","焦","赐","寕","𡺛","遏","粞","奣","嵌","𬗌","𫇆","䅎","圍","𭭧","𦝃","𧦱","絫","𬈋","翕","𡩙","兠","𤉢","䏾","𬯎","𦥭","掾","貰","葬","軫","爺","孱","掔","祿","報","酤","椰","㖾","𱋋","㲜","㫷","腔","㮊","靓","𬮈","𠤤","朁","雋","厨","黹","痣","𫾼","𥟁","禄","惪","𪸿","𧆲","媠","𨳞","就","𨕖","𣥿","䖭","睂","掌","𫣅","飪","椅","猌","弼","犂","脺","𨔾","道","鈐","㛮","堤","渜","彘","貼","属","𡎐","萲","黑","壺","𬡗","㗊","𠶷","尞","㥥","㣫","殾","惱","朞","棤","棥","䏽","𢧐","𢁆","𬛳","詋","粪","湔","蛤","𭡥","𤦡","登","旑","雇","棊","頇","棉","萱","寑","敞","復","棋","鈍","䇨","琪","𬪌","發","䓢","替","𫤱","𥬯","葦","皕","揖","𦧚","𮦉","𣦃","覃","暑","蛓","𭪙","毳","𦐱","𡥷","閑","𠸜","菐","稀","𨥏","溂","絶","䆣","跒","猶","𭦟","筓","㴖","𢝔","蛛","喪","筍","𡍯","溉","剴","䖵","𬛥","𫟚","屡","𨠠","閕","絢","𡩘","㙓","𦤑","聒","惡","蒂","傘","雁","𦕬","暏","㪘","斮","遐","惢","㓕","祼","葶","葡","睆","椂","𰞴","虛","趂","棹","𠞖","䄈","軨","尌","割","䘮","𠬁","雱","𠭥","𧺷","廋","𢽵","𤉭","壹","運","焚","畱","焰","渥","悲","敧","𬝑","短","稌","𡺥","𣔂","閗","𤊱","猒","稍","𢧉","𮥹","淾","禍","𨥌","最","棵","揞","𣸹","遀","鄕","揆","智","循","悳","貳","喜","湆","傕","極","焯","等","葍","焝","落","缂","富","棕","𫤪","飧","欽","猲","椎","斝","𡙕","萬","㨗","逼","凖","奡","戞","策","𥹫","𡞣","僃","𧯡","善","𭄁","寓","𪽗","補","葑","𢉳","湖","㠭","𥦕","𢍜","琹","㪔","牚","雄","㝢","𨳚","𥬵","黍","嵐","焛","詐","𧰼","寍","𢄉","愕","筆","联","渾","嗢","斐","𡩏","絰","棐","䦎","猭","惠","費","湿","斯","臦","渝","䙵","博","㥞","給","筵","飭","項","寔","堛","滋","晴","𭀭","𦓔","焸","𠷎","牋","朝","蛔","𥭅","盙","軽","畫","超","寋","棧","𣦅","隔","𧵍","嵬","𣣖","臷","𡔯","缊","詈","婺","無","𦥯","筏","絛","奠","鈘","𪯎","粥","勛","䓗","臯","舄","𠔥","𦱀","𡍬","葉","禽","葚","葴","𢝲","測","椉","䓧","蛬","彭","鈔","巽","皖","𧹞","𫲪","𢽶","雈","㔸","崽","𪐗","窝","𦀎","減","斑","𤲅","葵","葆","𥚎","𨈭","喬","訶","棨","跛"],"20":["𩐍","纂","饒","𫬲","懺","𬋝","籋","譽","譱","𬁯","籍","騫","蘭","覺","贏","㒹","𩅸","㶐","𩕆","騰","𣍘","櫬","𩐋","魔","𨐼","顡","䨇","耀","羺","籌","𣀦","飄","壤","舋","𥵸","躅","𪠛","蘖","𮋖","甗","譬","䢉","護","䶗","籄","騳","轝","馨","籃","䫫","黨","𨶲","䳬","顢","議","嚲","釋","𪑛","蘦","驀","灌","䊮","竇","鐐","鐀","罌","闡","闥","蘥","寶","觸","齡","𪃍","霵","獻","矍","籊","鐘","競","𰆬","黁","𤳳","㰍","𩪏","𣫞","蠒","𩐎","瀸","𪚰"],"9":["恠","胜","𬙬","峙","訇","𤇏","𦊆","祢","壴","昧","後","𥝤","垧","型","𠱡","𭣩","相","亯","昺","𡬧","矜","勇","度","胡","𥘿","咬","羍","祐","洳","奕","浊","㓩","壵","𢈏","𢈍","洟","垫","𮃹","𫨻","𡘐","炭","発","竒","柱","𣆉","𢍄","胥","𤇘","𦍑","兗","変","𡥞","郤","𥩝","䂞","𪜕","洵","𤔄","宦","県","贷","垔","𰴨","𱰭","𤇕","紅","𮧯","鬼","恢","𨊠","炡","𢆔","殃","厙","㑛","𱪲","适","哏","茵","枷","昫","𡘚","𠃴","𦏾","歪","徇","怘","匽","拾","祝","厘","𬛸","㔜","䆖","侰","𭴘","㲋","宫","𱼭","酋","帮","郗","茛","𤽗","𭤯","𣐩","胎","陜","𤰺","送","盾","室","荀","衂","茘","𪿈","咨","𦏺","𠚏","查","垠","𱦊","軌","莒","修","𱒛","𪰑","𦊁","𠜥","柰","虹","胊","䒩","持","䍔","𧘣","峦","𡱝","𤼧","殂","𪽋","斿","姚","𣅻","𢍉","荎","𭕛","㝖","眀","𠗒","帥","浄","𭖚","咪","鳬","𪤹","𡧯","泚","𡋡","𰙠","𫳂","亮","昶","荿","則","侵","削","恒","神","笁","𧆜","𰌼","𣅼","𭘍","𫊞","𥩞","𫦪","盇","柘","𱕻","𧈸","㿞","阁","陣","柖","𰠛","厗","架","𦤶","𮩴","𣭁","𣐝","𡱜","拼","垒","𠜒","𢨿","祗","宥","𡶬","𠱭","𬾐","革","荥","𫋲","美","拜","统","括","𣳨","狠","敃","响","幽","怒","匍","尛","𢇂","𡋣","䒦","恆","㝔","茈","巺","𢏚","𡋛","俞","㢴","勅","轻","荧","狊","𱕼","洎","𥝯","迴","㚇","指","亭","郝","𣧢","珎","茗","珍","蚤","𪽼","貟","虾","庠","𨒨","𡱞","𰋿","𱅑","𭴔","𫾩","𫯁","钧","叜","栆","盆","𮎰","𪱿","𠅔","柏","𠀷","茶","叛","𠥆","界","旀","𫯂","盃","風","帠","𥝻","窂","𥄎","𤤔","𣆎","畏","秋","衎","侱","姧","𡧷","𱚠","郚","𱝠","𢍆","䑣","𡱒","𰴩","侯","姯","是","㳝","㶮","𬏝","𦊈","荂","𢦶","𩠐","络","祜","贰","耐","耑","𮙥","耉","𢘿","茲","叙","㲒","怱","計","𢬊","屋","㰦","茫","脉","洞","𡋐","𭓩","独","陖","𪭌","垣","𫞰","胙","𭾡","㘶","㒸","胍","虺","𰙡","哈","茦","奏","𭩮","洴","𦥚","荅","院","𫋴","𣴎","俥","畎","洏","𡶫","突","䆔","涏","𡇒","迺","𢆓","𠧱","面","卽","𱬹","咱","単","𥫠","虽","敄","囿","柛","𠧪","𭺿","㢲","怨","𫢩","𢼉","卻","荐","匨","𥝸","䢼","祚","𤤯","𬚓","𤰫","䙲","軍","荔","𠣞","𮠖","贺","陝","𤤤","㧁","𠱳","䚯","哀","枯","厚","哖","项","品","故","䀛","茨","𡷈","茖","𧴧","𬽊","呰","恃","匩","紇","眇","结","胞","巻","㚅","前","𫝎","绚","彖","䊸","𢙇","𠡠","虐","乼","孪","看","𦊋","䖉","临","𱺸","𢙥","𥄈","觉","既","耍","食","紀","𮓷","春","䍒","迸","皅","𢙣","𤰩","𤓿","𫊥","𡘜","胖","急","査","𱏴","𭅋","笃","胄","耷","窆","𥄃","㑞","珉","㛄","柄","𦭞","𤽈","韭","昜","泵","甭","𱻲","退","秔","𱕺","級","㝁","𡴎","茹","𥄉","笀","笈","某","乗","砭","沗","𠱯","闽","科","贸","矦","炯","览","尝","禹","𡋑","姿","俊","𬡊","𰮒","拏","哂","轱","映","𬥎","𢑚","将","𱪵","貞","盅","星","㡿","𫇮","俚","洆","眉","𰠭","郡","柿","𭇥","㕟","𣆑","𭚬","姦","宣","𨊢","恨","逆","𰆄","㞕","费","曷","臿","㿽","剈","韋","垢","勃","𨊥","耇","𬜪","𢓥","叚","𰦫","娄","彦","亰","𥸭","弈","帣","𦭓","畐","挃","𣳾","显","庣","恪","逃","挖","说","卸","拶","拴","𬙙","垚","宩","砅","牵","𱀋","毒","弯","𦚏","𡧱","炫","㚆","俎","珆","𡘒","眄","昬","𰄯","迷","峉","𰫘","𮉰","𡇞","冟","𣆊","𠭃","爰","荣","𪰖","𫀄","挑","竿","𡿺","律","𭓯","𢍃","𢘻","信","娃","𦙲","𡔢","荏","昨","𣴓","𥄕","草","胋","屏","洼","𢦦","炢","冒","𠫰","秌","𭥫","癸","𢏝","便","追","郞","㳞","施","𦬸","段","𱭏","𦭧","荁","柳","𬮦","𤰸","恍","冠","骂","係","𭃤","洉","威","𥙊","𰶱","茍","弭","𧟥","𪟆","欪","咠","虵","彥","爯","𱅐","𤓾","𭥨","俆","𨛡","𨛪","𰥓","恬","俐","荟","怠","荖","約","祖","𰩬","𠱼","畑","𦚋","重","须","𤇫","盼","残","巷","羗","芔","𠜤","凃","除","奎","羿","矩","㽚","𤱊","洽","洌","𭺾","要","拱","穿","毗","庭","玲","荄","𤯚","呲","砏","𦭕","宪","𡷇","皇","胆","茤","逄","很","研","赴","柬","𧈪","怎","𣢟","𫊝","専","𠖇","洗","咸","𫇰","昴","桒","城","敀","𮂱","訂","钦","祍","𰀎","茧","𭽼","茸","姪","𢬇","炱","𭼿","觔","㚚","𥎩","范","闾","𡋍","𠫵","俄","炶","胐","爼","奊","昭","荒","洹","𭠃","奓","活","𢈊","𫡙","毖","𦭤","剋","𣐉","荆","庛","𦬾","㓧","舁","𥎯","弇","𥤹","𪠈","𦚆","柾","荘","𠱸","𣐥","穾","昰","绝","洀","洪","娜","𱙎","㘸","炳","𮥴","毘","𦊄","柤","狱","𢬈","叟","拭","迶","钟","𢍂","点","昚","垕","茿","契","𧈹","恰","促","䏣","泴","柑","孨","复","兹","养","䀝","𤤴","贱","𦚖","㓨","𫵚","𤔆","柯","勁","扁","思","㓂","𠨚","音","厖","甚","侻","陛","待","栈","𠂷","𪾋","差","浐","栄","香","頁","𭾢","俗","禺","南","姜","㤗","举","昱","𨹧","𰑓","挺","䂝","𡇟","洿","𱖤","茴","䖟","泉","洒","枹","斫","眂","郢","𬾕","𧆞","恼","姞","𭎘","咢","䀜","𦬺","𢓤","㣞","𠱠","荑","乹","柔","奐","虳","紆","盈","秏","𱲋","𦔻","封","𭭟","𪵻","荃","𡧩","洐","𠗏","洋","炮","𫟈","耎","紂","胤","𧴦","䀗","𥸮","𢒎","帝","贲","𪠇","贵","𭄩","𥘾","保","𮓛","𣥤","首","陗","皆","背","衿","𢌴","𡧰","殄","顺","𦥛","茜","𪿒","飛","𭥭","𢙅","𭎙","茟","勉","贳","𫀩","洝","宨","茙","总","𦚉","𣅽","衍","兪","畓","穼","哉","𡬫","𱽗","𤰻","𢈔","咿","𦘔","俟","𥸲","带","癹","迹","𡥦","𤝵","陟","拯","𱒢","粀","為","津","𤓽","盺","省","柺","峑","凾","䆓","𥄗","亲","染","𠁭","昝","匧","𦍒","𭚖","垥","姳","𥸬","敂","扃","㞒","逅","胃","𥄧","种","䎛","洫","枲","类","𣄰","炰","𣆂","缸","荗","昷","砉","眊","𣢜","剑","𭣦","𮂸","𫟯","战","㪅","𡘑","柭","茺","屎","客","砍","珀","柝","負","𭛨","𭩲","剌","政","羑","剎","派","枼","孩","洛","𫥎","𢏔"],"10":["莙","笔","𮠚","𱖪","𭻉","𮊂","𪶀","紐","𥬇","透","𥁘","𤱍","衮","素","晒","𭖨","𣴠","起","貣","𠳬","𰦖","𠅜","倩","剡","莊","𢇁","𰤷","娳","索","蚕","桧","敇","㫧","凌","圅","𥄳","准","蚊","厞","眣","𦚣","荳","𰭍","𪞁","桝","称","敉","哭","羔","笄","肁","悎","釘","歬","氣","帯","倀","笋","鬲","𭆞","倝","秧","亳","宵","𨊰","晟","釛","𥄷","翅","虔","𪧐","粆","羙","涑","徐","料","逋","眠","𫊫","凍","髟","斊","郵","𰋣","捔","𦮋","脂","夎","扆","𢓰","𢚘","𫪉","𢚸","𮎁","㫥","閃","𨓤","𭭋","辂","䎡","躬","凋","峷","𠅝","㰪","陳","倓","飢","陮","𰗣","挨","𤯟","𧙃","㑫","峭","秝","𣪈","𭤶","顿","㫬","陪","郰","倭","𧥢","𠫹","挈","䒹","𡇢","扅","紊","𮏄","牂","𭮪","倗","诸","𭥴","𥩥","铍","倦","烋","屑","𤔌","紛","哲","師","恳","𭩶","陶","衾","𦚟","釗","㫭","𠒖","㪉","孫","殷","𢚛","胷","息","流","𢼧","留","挐","租","借","陵","𣐺","途","航","浱","扄","𡘤","晉","笒","朔","𭭉","艳","𠓭","𠳮","𧮭","屓","部","彧","𭘧","砳","𣆟","𥞔","耊","剥","𡘝","𦮎","𤰇","辱","𣪊","㑥","𠣧","𥾸","耽","鬥","𤈜","甡","盏","俸","海","𰄔","𪺮","𦨚","拳","笍","狸","埃","𬓥","𫾬","娠","毦","蚔","畠","𭆆","㓒","㪿","烏","𬺞","卿","𢈙","㓯","邕","涉","𩇧","袁","烟","笓","荽","𮊀","挛","𡷰","浼","盌","圄","倶","𥸷","耘","䒸","消","盎","帬","島","𠖐","𭖦","𡕦","栗","𰇩","娣","𭃳","酒","紗","𫳇","𣍮","原","𥩮","被","峳","𣬈","莫","𰀦","聁","娩","𦤃","倚","娥","𡘩","柴","𠖏","顽","唇","𬶀","唆","𭕞","𡨚","捉","𡨋","純","谈","冤","𤔍","席","𧉘","徒","莹","𬆣","鿄","涖","芻","脆","悖","軒","𡨐","珦","紋","倉","𱒱","剝","𠣬","瓶","𢼸","娑","致","倐","𥥐","㽜","笏","𥅌","眛","峰","聂","悔","𣂜","晃","悟","聀","珞","隼","䀠","脈","𦊒","捕","宾","眔","𡨟","剖","剔","𬜶","𰙤","𣁋","𢙽","姬","㢆","眞","𫦂","𰺅","陰","䣅","𠫼","𢭳","𭥯","哩","弱","𠥶","𤕺","屐","栽","𫺁","𬀴","𨤾","益","恁","贾","𭔰","𡋲","冡","𦊥","𢼜","𦊎","俶","𬇦","哠","鬯","䓁","浛","紦","振","𮥆","釡","桌","𨓜","党","欱","𡌓","𧙏","通","釜","座","莉","浽","射","秩","𡋵","𢃋","𦊚","𨛼","𥁑","𭙡","𮈄","𠚒","𢓸","蚉","埋","𧴫","𬬺","𪣣","涄","载","納","𢇅","個","豺","骨","𠙖","𭜫","𠩵","紏","容","竞","病","隽","𪯌","扇","爹","涌","荷","䎳","套","莽","恧","𮜿","桓","袪","𡝌","𫐩","都","窋","匪","𡘳","匿","烈","𦚶","叞","旅","皋","冣","莝","冢","𢀡","卨","珡","㫫","恣","笑","㕋","袍","隺","宷","𰛖","𫢴","宭","蚩","𦭶","砰","哺","倮","破","𧥧","畔","宼","紝","託","荸","𠂽","眗","𬙮","𣵡","娘","恙","臬","浹","桐","𣵀","𬁼","畢","畝","㕖","𫸳","眘","爱","這","勑","莧","烕","𱳛","𤼩","𡋰","疳","秤","𫆁","莠","脊","𦮴","𫝗","悅","𧰬","涅","敖","𡨄","孭","涓","𧆠","𣆫","𠂺","𬐚","陷","狶","𬯁","㬵","特","哥","豹","框","𠂹","莢","祥","曺","𥬄","𱰮","桎","圆","𮫮","埐","𣑱","𠲯","桑","𤇸","𱛩","欯","桊","𬒴","𰫝","烓","𫟎","㳭","𠳄","造","𭮩","耿","峩","挼","𬙜","秦","朕","荾","峲","栾","𠳋","盐","缺","冧","閅","𠅘","牷","𬻞","𥎵","娧","𥑭","浧","害","窅","巸","𡔧","𥅘","积","桍","宰","㤪","䏧","捚","耄","𭪂","郸","逐","𨳌","𰉯","倅","𭯍","宴","隻","𰢱","烦","恕","畜","𣐸","洍","𭍠","𭆟","𦮠","訓","𤇷","晏","㿾","𭜮","貢","粉","竝","𥑟","莤","羞","秮","𭿷","哿","逛","記","莨","泰","莭","宻","莟","旁","莞","衰","𱦋","恩","冓","竘","𰀕","倒","𭮫","𠡷","速","𧉏","𤇾","恖","紡","𡨈","浩","𦣣","䒺","𭜨","䖍","栱","𭭇","舀","𱥂","盍","𧉎","時","𨤏","𡸁","𰙩","𮧮","恥","軏","𫼋","夏","竛","討","兼","𤇯","圃","㕍","𤯅","𰲚","秥","晌","𦊜","丵","窊","財","倍","耆","能","莆","䙳","珠","浿","軓","候","眧","桃","耕","𭜵","𥁕","烘","效","𫹔","祘","栖","𦕂","𢆙","𡷝","莀","羘","屖","宸","狺","浪","晋","𣷚","恭","㼌","翁","恵","𱦝","𥥛","𡘲","莪","𡕚","莗","恋","𬜲","畗","窄","曻","尃","𬾨","𮮑","疾","𣑦","虒","𠳅","罢","䙷","𣑽","𡌥","欮","𭣯","紙","莘","哨","𥥗","监","𦚾","捎","耼","𣐽","𢍏","𠣦","逌","飤","𡭴","热","㖖","脩","浦","𠳒","根","𣵎","𫵼","案","狹","訔","值","𠅖","秫","恶","峯","莑","𨺅","𥄱","郭","核","𤽤","㝚","𢔀","陸","倠","珧","虑","𦮔","烜","𬂧","娏","𥥍","𢭎","莖","袅","栢","𦚧","𦒿","軎","倫","校","𪺽","烝","旃","𡨞","𧉊","𣬉","𫸚","𬜷","𧴮","恐","畕","𠩲","贼","㻂","𠊅","涕","𢓱","𢼴","栝","𢈱","従","砧","𮕩","逢","挙","𰞚","斋","𮓸","朗","胸","宽","訖","𫂵","挾","𫩁","浮","𧙍","𧲣","晁","𠳺","枽","离","𣵣","𠧴","埀","𡘞","高","𣆗","𭙜","竜","𢼡","𤤿","畚","𥄲","耻","般","㶷","倘","莁","𧴪","剗","浸","冥","𤞻","𪠋","針","站","资","𧴲","样","殊","𥞓","娕","狼","荼","耸","庯","𬜯","條","𡥨","畟","𢚩","𧯜","䍃","祟","𧥥","读","𥁓","脋","厝","旂","務","𪸥","𣆪","𦕈","員","捃","浝","俻","龨","展","圂","窇","𡷾","粍","健","𡘰","班","悍","殺","旄","罡","𮩸","逝","悁","𦐇","𡨝","䉼","涂","𦍤","浗","𪝉","連","恚","桂","豈","𥥟","眜","䒱","㭝","𢍍","浡","预","家","馬","𣑩","毣","脅","珤","乘","凊","𬔰","䘐","𡴘","𢦷","钱","𭽎","𠳯","峻","浰","唐","𰯯","逑","眚","莩","書","剛","配","庫","𦮕","俱","𢓭","耗","难","格","莎","𥑥","𭜪","拿","浆","臭","真","栞","欬","𰀒","華","𤈕","𢃄","㿟","恝","𭰘","哢","宮","𥞊","奚","䢖","𭣱","𬊇","绢","垷","㱿","秘","𨊫","唄","缼","桀","挹"],"11":["𮋛","𠦪","淡","豙","猄","𤿤","菬","視","萁","𢛲","砦","寉","盔","窒","勗","笛","圊","雩","㴆","笺","𰮕","䧑","𱰋","𫧉","䀁","國","𰿘","𬋩","犁","𠋛","軖","𮏚","𭻍","𠝣","淸","𤕻","終","窓","𬀷","绳","𢛳","𫞫","萘","𭍥","㭬","鄂","虚","渦","訪","𣇄","脱","敘","䟝","象","掎","彪","淗","梧","猜","堂","𬑔","野","庵","𫟐","𭷆","𥁠","𱉥","䋈","𥹄","竟","棻","梨","婪","𠶶","菲","𨺵","彩","𰨥","𠶬","望","距","動","𡨥","𡘼","淙","𧆩","𮖿","㪷","尉","䂮","𠵨","船","偵","𥎿","埶","聆","接","悥","虘","曼","𧠓","紨","敝","袴","𱫌","鹵","𧰲","𫱀","斬","萊","𪺏","堃","盘","赉","菊","𫽚","𫻶","寄","𣶒","𫭋","𫈅","逶","淘","𦯧","逵","㰯","㳫","盖","𭜳","𰲝","𡨧","專","𠵂","𢉖","悊","𠧸","𪎊","𧦈","理","𦤏","埜","赧","䆠","著","𢜈","冕","殹","𡨼","𡇶","唫","啚","副","𢽋","𠝭","梏","𠵊","𢛧","谻","烾","婴","扈","𠣯","𧙯","密","𢉉","兜","𥏇","啓","戚","渊","𡞔","𧴻","𫤰","術","崩","𣪌","庳","𡝤","𦛱","窑","偪","𥬝","㢈","隐","戜","寁","現","𧴿","営","䏻","眯","猗","𥬑","㠱","𨤑","訥","𤱪","𠦬","組","萗","彫","赥","𢇇","旋","袞","𣨑","掃","𠊰","𡈀","堕","𱀚","堇","晧","掗","桼","𰇶","𣪓","𠶮","厠","𡮁","𤉄","𱏧","情","焅","鄊","𡘽","盗","牽","笙","窔","𡞕","𢉅","𭣴","𡕨","啐","啄","唻","𪡒","窕","偒","球","𦤎","剭","𤭃","涵","䇥","𣶃","菡","虖","曽","梁","躭","聊","𭾱","𤈿","𨟽","甜","㶾","徝","貮","勒","𡨤","婦","啇","梢","皐","𦰧","𮙲","𧴴","転","舵","𧴵","梦","𡙆","𰱅","乾","𨋅","捨","惈","㣎","絇","𢉆","惟","焊","教","𧰮","𬀽","假","鹿","䚿","添","停","𣣅","逸","悉","巢","悘","𮫬","貨","𠭙","進","鸾","𫩀","釣","𧵆","渂","朙","宿","𪲓","敢","婏","萠","𮔀","鄄","镺","淂","菫","𠊳","逨","淰","康","液","颇","培","常","𭓶","猉","梅","𠕠","𣪐","䇠","萈","𥒥","𥬒","奜","逴","晨","冨","𠃀","畣","剬","隗","旍","酓","𮮠","晡","眷","庻","阋","脚","蛇","舂","𧿭","陽","𢽐","𠁅","崟","𰶷","𢧁","烹","堆","患","䅇","𭮰","㭪","𥥪","𤈫","𢽊","衒","畤","絁","㣦","𨾏","頂","𧯞","笴","𥅥","𨜞","𧦗","堅","𠩺","焏","敗","𮞨","産","𨈡","渐","𰿚","涷","盒","偶","祸","寀","孰","救","域","隈","畨","𨊿","𮙸","焐","𬍥","𱞩","𤉋","粛","菛","𮏖","萑","笘","麻","菆","雪","祭","疵","𡙁","覔","赦","設","深","䝆","㤻","𡌳","𫈏","悠","崗","𧙿","𣪘","𥙷","𡘺","㕘","𫔴","𭸋","𢈻","猫","𨊴","旌","崬","崔","隌","菁","寇","𡍏","亀","淺","貪","捼","掮","菱","𤕽","㭰","堵","𮕱","𬂴","屠","𱥗","菿","梖","𭽪","𰲛","㽞","𥿄","𥑴","圇","帶","第","堊","做","涯","眽","偉","唯","張","𮍏","庾","萧","职","屜","屛","授","𣂞","维","𫵠","寅","淄","𭾁","㒼","𠁳","萅","𣢾","率","𧉾","彗","𢜤","𧴹","𥥭","𭴷","區","豉","䧔","毫","斛","缽","訣","着","萌","𡨴","梩","𥥵","戝","梟","掩","徤","掘","寂","䆟","𦰌","菟","敛","㿡","晜","𰥡","𡕩","渄","㤲","𮥶","捻","閆","𧉴","𫇿","敍","䖏","𦰩","問","猛","𨾎","掂","軗","𱻱","𢔜","𡘷","晘","勘","𭾲","圉","𠚕","银","參","渃","戛","厡","𰱃","𤼭","魚","娶","聃","閈","𦕒","𠵦","𨓿","脯","桮","菩","掽","隅","𩂀","䚴","隂","玈","𢜊","琇","寃","笤","焄","𰺵","族","𰚋","捺","欷","𡭽","逮","𢜏","累","焇","𡝼","猖","許","𧆥","翌","廊","𥒐","菶","淖","𫃟","眼","粗","𥁞","鳥","绵","晝","淠","𭦌","眾","笪","𪺞","曹","惨","旉","𭦊","笯","𭶰","帷","笱","匙","𣪍","敓","菹","萃","𰂙","㝛","萆","𢒗","𪦾","偸","敕","𡥵","匮","趾","𣇃","𡌭","𦰟","盛","𠁁","萦","䚺","章","探","梔","崙","過","萵","斜","𨤐","𦯆","䖤","𣷌","淋","䅈","𮍖","啉","捷","𤱺","殍","梵","庸","殻","猪","菖","啟","貧","晦","菉","𥥴","淩","凰","𫁹","晢","彬","悤","畧","罣","𢛢","符","粒","𢉙","㷀","𨱝","𧆨","𡘹","𧟪","䓊","偹","𰭌","奞","黄","菓","𨾈","旣","勔","㝡","萄","徙","𭾬","䇣","𮏝","掛","减","𩁹","㴌","匏","笞","淜","𡿿","匐","𠝻","㻎","側","𠭖","豚","𬝉","𥞤","異","悪","紵","虗","紬","偃","𫪡","崇","𩵋","菀","崑","领","焉","淦","涪","渚","𤱵","𧉥","圈","𩁿","𤙭","萎","淅","痕","随","渒","猚","䅆","偏","营","𠵥","雀","淶","㪍","𡨦","痔","𦯕","𡌦","脖","勖","庴","貫","袈","桶","階","𢔃","脣","蛋","䎆","淮","瓠","粜","笮","梓","習","售","䍘","𥎽","𰩶","淨","捭","叄","商","𨔛","𦊷","𬯆","偷","𬦈","𩇫","斍","脫","𠁃","捽","剪","𣇓","斎","淥","笡","細","將","窐","措","產","旈","軝","羕","黒","淑","衔","𢼾","規","𨳐","𪟊","𠙚","清","𰶳","𤋳","鄉","笠","處","惜","𭄶","㝝","𠋣","隆","䙴","㲘","爽","徛","捧","㹿","梫","得","欶","㝠","𣇀","谒","𨟻","偘","屚","𤰈","啫","𦘕","執","掉","婉","庶","排","𭽀","𧆭","隊","𣂫","紹","𫏳","𨱥","𱑏","𥹙","𣪏","𣭵","偎","唬","𦕓","𠝮","移","推","麥","混","禼","脛","𰠀","𣁐","梗","殸","㳿","猎","𣥶","強","梞","脘","䚻","菌","偽","貶","断","基","啵","敏","渠","㳟","恿","䝨","𦧔","訟","婆","䇤","𱁈","𤉐","粘","𡮂","頃","䄅","𡹐","硃","𣶙","𥞫","𣇛","敔","𥬥","𪲖","𠪂","逩","欵","閉","奢","涼","琍","責","𰥞","𠵛","匾","婁","覓","𪯍","笼","菜","弹","䢙","𤫶","逹","啬","莾","𠗦","笥","略","笨","𭦗","髙","𰶵","翏","傀","𨔍","𬜻","隋","酖","㓱","𩚇","梄","欲","𫳐","𭚽","𣓀","𱡘","阎","悼","𰓶","㸔","絅","阉","票","𠶋","從","𰗧","䚵","菳","販","軟","菴","惮","𫾶","崖","甛","淫"],"13":["勤","㐮","𠘂","溸","勣","僉","蒙","歅","閙","䇾","鳯","𭵝","溓","𥭷","䀄","𡠓","𲈩","寗","数","厀","𢔸","豤","椹","楺","煢","瑜","愛","晸","瑟","䑓","睪","㨨","煔","酫","㮣","腾","睘","筞","𩚴","貇","虞","䝱","遝","旒","亶","蓽","虡","閜","楷","𢾟","筭","𦳃","毼","詹","𨕞","𡔷","𭅞","䧟","賎","遘","𬆪","愍","勢","滂","預","諍","𤊸","虜","嗐","粮","𭐖","𮮰","當","衘","㼱","滈","𢾍","𡔲","碁","遣","筮","睹","牑","𡺳","𤋎","搸","𤋱","𮘎","𤊽","腦","蓐","媷","亷","𪝣","睒","䩗","𰲡","𥭽","塞","魁","頑","遙","摀","雹","麁","嗚","𭫄","𥇡","𢟍","𢊁","試","煨","𡺰","叠","剸","㲄","貈","甄","零","𬿫","蒯","農","歀","𮯙","解","𥪖","楼","滅","獁","辟","閠","罧","頍","榆","蓋","圓","𣔾","䪞","載","塩","輅","𧱈","𭛂","窣","𡩠","微","蒪","𤕤","𠦶","睡","腸","孴","蛾","誇","鈲","歲","豋","鳧","蓬","𪳄","㗖","𦋅","𦥷","煞","𬥈","𧧑","賃","赖","鉄","𢊃","满","戡","寛","會","楬","𧵩","𩾕","𤗚","翜","𫑨","筶","𪫕","蓍","𲉜","愽","愁","該","痯","𬯻","溯","弿","𢐌","鼠","兾","隡","蒹","溜","廓","源","𧵽","𦴹","碎","筨","缚","𠍘","溤","頊","與","𦴋","滔","蓝","𡠋","𤠗","碓","蒕","𡲬","詳","𥺀","楆","𨻶","𦀓","業","喿","䢽","𡩹","𥇨","𢾕","輊","群","𨠭","殿","㼫","𣪠","𫁾","媽","𪧟","嫌","溦","𥹺","睗","彀","羨","槩","𭔺","稕","𰙔","槐","㰻","瑞","雺","𡬺","照","詧","窞","聘","牒","嫈","豦","墓","𡙢","颓","𤾇","碖","𱏵","電","𩑤","痺","飱","㙛","睦","竪","幕","猷","蒩","𥂀","肅","滉","絹","舅","稤","蒿","馵","𥦮","綈","𢞭","𡻎","煉","𠪘","閚","奨","腮","觧","椿","𠨣","剽","煖","䋣","跬","資","躳","福","𧋠","𦋐","暘","鼓","賈","盝","盞","𥇘","跱","𡕰","搵","𤲢","筲","路","勠","廈","毁","蒦","肆","蜇","腷","𦤔","溫","𲊦","跡","𮘌","夢","蒲","廌","歳","煩","𠅸","蓁","輂","䢅","獅","𣺎","𫳭","𦳝","睢","暈","傻","𠣻","盟","禁","㮚","新","傳","稟","𰚃","號","𣪧","𢄔","愚","𤷭","鄣","禓","傫","雍","𦕾","躲","𫁒","置","鉢","彙","搶","窡","斟","鳩","𦞅","𭸢","𩐁","想","𱢒","遥","𫈧","𤋯","𠹝","献","跳","寞","鉉","楽","裘","𥇴","𢍢","豊","債","禀","𡩧","粲","觜","骞","靳","𣹰","㷐","敫","訾","稜","蓉","𨋰","搏","频","溺","裨","煴","㙜","跣","𨽶","𡕝","感","痳","𠌵","酭","𤦲","蒼","𧠪","睛","暓","閞","綂","㨦","剿","𰢅","綏","嗎","頓","寘","𤋁","𫖻","煥","靴","筹","較","準","𨥲","皵","暐","𫈦","鉤","㰹","鈹","简","貲","蒮","嗀","廉","䍜","𩉨","蓆","𱘥","傾","䋠","搕","奧","蜀","蓄","碗","壼","痲","匯","畺","䇺","𧆾","塢","𧧬","䇷","蒤","𩉩","煦","楢","阖","䍛","𭵜","𣮿","蓮","溧","嗔","裊","㚠","䐑","意","毀","蒸","𥟦","罬","𬕍","䧹","稑","颖","触","詵","蔭","督","𣨻","塘","𦝲","𤋃","𢱭","𤋮","艂","𢊊","經","綑","粵","漠","𦝚","腩","暌","阙","溘","署","𬐧","歈","艁","䅗","𢲛","嗣","歆","𡻕","遜","𥁼","歃","誅","𢽿","𫎴","𥭴","溪","趍","𡈏","𣕡","楞","楚","𢧜","㝅","罩","䇿","𩵎","椽","楫","𢊂","詣","頒","䝉","麀","𭪿","𮖄","筴","歇","嫆","碑","蒡","稔","賊","辠","㬅","義","裸","𥭗","雾","損","碍","𥭛","𣺦","鈴","㴱","𦴼","閘","鉏","𬁅","𥇛","滛","㷔","𡩟","𤿺","甞","亂","話","黽","䡔","𩡱","暖","幐","筷","摇","節","媐","䖒","摸","阘","羣","楊","稞","䣕","𩂜","𪪷","𨋬","蜆","隠","𠹈","腫","稗","𠹜","溥","裔","𠌶","罪","𭤁","𥹷","誊","𥈀","𦎍","愩","膄","𩂕","窩","筫","頉","鉴","嗇","禋","䁂","𥂁","瑰","𢞍","𮔉","搞","嗃","暊","窠","煌","靖","㴻","遟","飾","蒭","幹","愈","雽","楤","媻","𣔵","裏","稚","詩","稓","楙","慈","蜂","𨕵","豢","罨","漣","舝","遠","魂","滥","溰","暗","𨕥","𭿃","聖","滌","廍","𭝤","雷","𨾱","𢊆","惷","園","鉗","稣","搉","塋","煙","魝","楘","溶","窟","嵩","𦥳","雉","煎","搆","輈","催","塍","𩰬","腰","搖","䣱","酬","䅟","𠪔","際","𮃔"],"14":["蔑","𬛭","鳶","𧟶","𭀰","牄","䣈","僕","箎","𡡅","箩","㗬","槃","漏","𢾾","雐","閨","膋","毓","𱢝","鳴","對","綿","䋲","敲","緂","䛣","𠎤","睿","𡙳","蔄","鄰","辣","樋","𨴠","𦞽","𠎳","摳","䛟","綦","翣","寥","毄","寬","墊","𪷂","墜","㣃","漢","踈","蓴","𰮫","模","𧶉","貌","𥺤","䡛","箒","𥠁","𬄀","𣘐","獚","緒","蓷","熬","髪","駁","𥪡","𮅕","鳳","愬","𠻝","竮","榴","銀","䦚","阚","𤡜","韶","寢","䈇","𭫝","㡭","𢊪","隤","䯉","綜","潢","聞","端","僜","𠍾","滿","塶","瞍","嫖","語","戩","鄧","臧","蓲","兢","𠪩","鼏","匱","㺒","箸","𡬽","嫩","𬕏","磈","甉","窬","靘","𥺘","戫","䔍","翠","𫒘","夤","𰝂","奩","綢","蓼","暯","𰰎","蜜","摠","𨐚","賓","𡏳","𧶐","𥯌","嶌","𦁉","銅","徴","塷","𮮱","㪣","稱","蓺","疑","廖","僭","𦵵","賔","構","𫢀","𪓑","𩫃","鞁","歰","雑","麼","𭧂","遬","槖","竭","碭","夀","𠃅","𦑕","銚","𠻮","鄭","摷","𮧇","関","箅","緇","榼","遮","𠼗","墉","閧","褐","翟","緐","熊","馽","鄲","𥈠","㕑","厭","歌","説","屣","遭","熏","熖","隣","敳","截","磋","窨","𣣸","厲","朢","䅥","𫗏","歴","𧳑","榫","熙","綠","僡","睽","𠾧","蔚","銜","𤯳","㓗","蓻","寨","蔽","複","赘","槁","銃","塵","圖","裹","𧱔","鼻","暮","箇","歉","𫮛","蔴","𬕟","酸","熈","𩶷","𨁡","搴","殞","𱏬","𠪚","閰","榮","𥠖","輕","誘","腐","需","暢","嫚","廔","輔","豪","鲜","䋰","㥯","𤛉","鲞","奬","滷","㢕","䅡","曅","獄","𣻢","慁","𣣴","𢕒","𭔽","𨁍","監","麽","瘣","箕","察","慝","𣦒","綰","𡻟","蔓","蔵","璃","魄","𦁎","𡻦","𬆭","䜹","蔥","雒","䝳","盡","𫄻","﨎","𣂺","𦞧","錚","魅","說","𦵮","𢾰","稭","㥽","愿","𦖞","僞","漚","暜","蔈","𥯀","碩","𮧊","𡪛","㥷","肇","摹","𨾴","𫎇","漸","寧","𣣻","塹","㼲","蔕","廣","㷠","㕡","䈁","𫏬","旖","𤲶","緊","𤾊","綽","𭫒","榦","𨲆","彰","閤","摺","誩","䎩","𫡿","嘉","㬎","緌","𦖑","凳","𩂩","閩","閣","㢡","暨","滾","齊","摘","養","綺","𫀽","𧇃","綾","𮎙","蜝","領","奪","槅","𢇍","誓","斲","實","夐","耤","䚂","厮","壽","綝","𫜩","屢","𬂉","罰","箆","𣗪","𦦀","覞","歊","𦵯","䧻","𫈼","凴","𰍙","慕","嘏","𫃅","漮","斡","𠪨","滬","暠","爾","勭","𫵆","𮖐","牓","寡","緑","𦷊","𡠺","墮","寠","𥈜","勫","𦩎","𩂫","榛","𭐫","𬈥","誨","曄","僧","算","疐","𰯲","蔧","榖","榑","䐜","稨","𥯄","冩","𤬌","鿿","蔗","舆","䰟","𡼁","誦","閭","蔞","嫰","蜚","慱","静","裴","暱","蔍","𲄡","辢","𢒩","慟","𡼇","搻","膏","槀","酷","䅠","𬎼","漻","甍","碧","漫","誑","滲","𦞼","漅","箫","裳","𩾪","榜","𧇄","𦁤","嗻","𤾓","幣","䊍","𡡉","漂","赛","頗","𣗥","賏","網","隨","趙","䁔","㝬","𥮗","慚","綱","𧇊","弊","銓","𭵠","𬡤","稫","𤌑","𬃷","㷦","暦","螂","霆","皷","𤌹","𧨅","隧","豩","滯","𧛱","畼","𪷁","𥈪","𰚫","酼","綵","舞","銛","𠼑","𩢃","熇","𧱏","朅","䆫","漱","𮄉","𮥟","箏","團","種","滎","𱾂","𪳐","𢊬","辡","盠","𭗐","精","嘗","蓸","𡻷","貍","聚","㪡","箑","𢧤","𠢧","𩾦","綮","稳","馼","𩾯","蔡","嘆","𤖏","塾","𬖥","蔺","粽","赫","歋","𪏭","瘦","箋","箄","熒","瑤","管","睾","旗","僚","慐","䲨","箜","蔣","適","犖","維","䟽","𥪝","臺","瑪","漗"],"15":["横","𬓶","緾","毆","請","鋞","䔥","墨","𤍾","暴","億","劉","履","𬴘","𭐘","题","蕩","蕊","摩","黎","鴈","撟","踖","𪏯","豫","𪧨","𬥉","䔘","𦖢","濎","蕪","瞐","蝥","䴡","𥝅","殤","䝿","賣","甎","蕇","䴢","㦄","熟","𭤊","樊","慼","憎","𥡂","暫","䈞","暹","歎","德","鋭","𥧡","餒","審","確","𨗉","濈","𣙺","慰","𢿝","𡕷","噓","影","緹","敵","𦂳","練","談","霅","𨽹","𦋹","劍","衝","慙","噴","𩒛","鋠","戯","𫕙","儉","質","蝱","醀","誰","廟","遹","𱿒","𧤅","鋂","遲","𧍣","𢵤","𥻊","樠","稽","頡","𮥼","賤","磊","𠚛","𡔽","嫴","穀","輦","𠆆","戮","鋪","頝","撻","𱔞","樞","𦋺","𢡃","𭵼","緜","頣","諄","瞢","𤨝","霄","賦","瑩","𥻡","𤕦","𫯺","稸","蕃","䈎","潭","廢","𥠷","𦂌","憕","澍","潁","潡","㜦","𩵢","潕","𮐹","羯","鼒","槧","箴","樁","骹","𦖻","𢿙","慮","遷","㙯","輚","播","鞋","篇","𮚋","蝦","諂","𪮫","鞍","毅","𠾳","蔿","𢒫","閲","槯","𭮼","韯","魯","蕈","𨽻","豬","罷","幢","鹝","頟","暪","幡","槽","槷","憂","憃","䝾","翫","撜","𧇖","𡑅","𭭔","覩","𧣽","䦝","蕋","㯎","徹","㢖","選","潦","𥉁","𧶠","畿","潐","䝺","豍","儀","𣾎","僺","論","踪","寫","𭍳","䋶","㢘","豎","槾","𦂱","䲷","瞏","篆","稾","颜","撈","𪐡","𩾹","賚","𩛬","廡","輩","樂","醉","輪","𦂕","𦎫","斳","撨","𦂺","𡙷","𠅀","蕐","諑","羮","㯋","慧","層","輝","𩾷","𦸛","輙","𢧵","緩","𦟝","賡","䈟","歐","𠒶","導","㽓","𩾵","幝","盤","蕎","𦹏","廚","駕","噧","儋","𪊘","賜","𭫪","𨤮","蕁","𲎋","劇","槮","𭧘","蕫","閱","䁝","奭","遺","霈","𬑤","潸","𣽨","嶚","慸","撒","趣","䗍","澄","𢕪","撲","餘","𢀩","緘","潛","𬹝","鬧","䔡","擒","憨","蕙","頪","𡡾","窮","翦","𬿵","靚","臱","鋤","編","皛","齒","趟","𢿌","皺","巤","麃","𦖩","閬","價","噐","慶","膚","𢵄","畾","𫔡","蕚","𬞕","辳","儂","數","澁","糊","虢","𡙹","𬙸","鋒","䠂","磐","槱","嶴","賛","遶","𡚁","𩃏","緼","嶲","罵","𡪺","撫","緣","樣","調","線","慜","勲","黙","㵕","𡙸","𦤝","寮","𡡴","𥂈","耦","撢","槳","𢿐","䰻","賢","𠏉","𫉍","殢","㒒","潪","歔","𭙵","踏","㩅","撮","諸","潜","彈","儇","醁","膝","𦦉","衛","險","潗","𠾂","厱","徵","匳","廛","㽦","樓","𡼡","𪎷","標","課","褢","潟","𥻆","熱","緝","範","㝯","翬","銽","貎","緖","𤎉","𪔅","遼","𤍳","賬","𤕨","緙","𬢱","敷","𣤓","霊","撥","趠","邁","𣊖","𮖚","𩊐","𩒨","嘼","撩","𰸙","𱀵","犘","輟","澋","潘","蕑","滕","澑","膠","頢","𧡖","蕳","震","賫","蕨","撞","蕉","賞","踷","髮","罸","閫","稺","𩿊","遴","窳","𥻑","潓","墪","𢨆","靠","𦂝","箭","槭","憧","𦎧"],"16":["𥱤","叡","𣚇","𩶓","𦻱","穒","篱","篗","𰼝","噩","篷","疂","𲁌","熾","勵","𪚦","璚","整","𩃮","辥","樸","𪉟","蹄","諴","薟","𤎮","𩫏","䮍","𦺸","隱","憶","獴","薑","𦻳","䦨","機","覧","橑","錉","𧜣","𢍮","㙶","𧶻","𱹖","鍂","罹","麇","霖","𪏰","㷼","懜","澤","𠿊","赞","𢕹","儔","憲","𰟚","韰","薉","靜","賴","𤎭","曉","𣊡","頳","薬","薦","臻","旙","𩒳","𪫙","𫕻","燋","𧇭","頶","頹","默","闍","𨨖","薄","橘","窶","激","擎","鋼","縜","薛","奮","𡦢","篙","縣","醖","諬","墾","㬜","衡","龍","彊","橫","曆","築","𨽾","薊","廧","憙","嶶","憾","穌","霍","𦼔","獨","𥱩","𡚇","𪦨","𣛕","黔","衞","獲","學","孹","𦃃","𥱡","閶","𰕣","𪏵","𣿕","還","儗","𧎮","鴫","燤","𠁗","𥉾","勳","𮫴","毇","𫟪","橙","㷴","䫉","輲","𧇩","錄","䔲","薇","𡭊","𤬏","橦","辨","薔","嬴","褭","壅","觱","遽","𩿳","甑","盥","𧳯","融","翯","錫","窻","罃","𥱋","㱅","醒","㣈","褰","擇","㯥","衟","𦔐","燕","隷","澡","𪌜","營","篭","𨿳","𬄜","聮","𨤰","儒","𭾐","舉","磬","霓","𡚊","𢿱","𭟼","羲","餐","頷","錢","謀","歷","縛","鬳","翰","𮭫","器","嶭","𠔳","燐","頼","䨜","縢","燔","澷","鮑","圜","蹀","薨","穇","𩰵","𥡝","諹","甐","𭂺","燒","磟","擁","𰒲","辦","𬹥","𣚯","䔵","縝","閵","踰","薪","𫂐","錦","𥂔","㢣","蕭","霏","撿","薩","𦃐","䑞","𰏮","𦺈","螢","𨿣","憑","薯","濃","廪","縈","𮃣","縕","篚","穆","𮥿","䀈","雔","橐","虣","𣫆","駮","錐","劔","𭘸","𣚨","𤴡","㢛","錯","㽔","縠","頺","閻","篹","操","耨","𧜼","𥰟","儞","缳","𫨀","颠","𭻨","冀","頭","頽","輻","橧","薫","㔍","親","𣦞","録","樵","奯","𣚊","寰","𫄾","踶","頻","臈","膩","𠪾","𢐨","䳆","𧇨","諼","篩","𫴗","曇","𱅼","麆","𥰬","謁","凝","嬖","鴨","㯤","磨","醜","閼","錿","𣿳","䦧","𡕸","燚","瓢","𱤏","𮇷","褱","澧","薏","𢅛","駡","積","𱢬","薜","鍵","𩫓","諞","橋","駢","閹","黈","䰜","濁","彜","賮","霎","橤","穎","諫","劒","𢨋","𦠤","熹","盧","徼","𢍱","橆","膳","𢿨","頰","縫","篡","䲽","戰","𫲲","廩","雕","暺","𬪰","燊","𤯌","壁","穐","𧎪","餞","燅","嬐","篦","諧","頴","薎","駦","篤","澰","虤","𨂷","輸","㬱","錡","興","厳","𦃙","𨂠","鋸","㦔"],"17":["螫","薰","盪","䙔","牆","膺","𦄨","𤾡","擊","甕","斁","穗","邉","臀","𡽽","褺","𭄘","賽","顀","龠","𦓈","爵","謈","獮","𨪆","擢","藏","檒","禦","薾","𧝑","𩫗","擰","蹈","謗","謨","䩭","縳","濕","臨","𦼪","䉅","薺","點","㯱","擘","雚","闎","壓","繁","嬭","𦦙","𧯽","𫏼","𡚖","魏","㸂","麋","斂","轄","贅","戲","藍","𩫖","燮","氈","𧹳","𥱾","嬰","繄","𦗕","總","𦓃","濱","豳","謄","謙","韱","𦏁","𦄐","徽","闌","嚮","䯹","聳","㻺","𰘴","𦾔","嶷","鴶","𫶝","鍊","豁","穛","𪀲","濯","儲","舊","檗","謢","曖","鮪","䞿","臆","濤","𢩠","𡽫","鍾","燥","環","輾","薻","鮭","螻","螽","𧫏","斵","𪪧","懇","濫","𬒣","歛","篾","篸","縶","𪏽","糞","𭼩","魋","𦽦","鴻","蹇","應","霜","𩋘","䫏","禮","藋","㕓","䆸","𦦚","藂","韓","膸","購","𧪬","𫏛","霞","壐","𧷗","霛","鎾","𢣭","輿","擠","檜","聰","𥂮","繇","講","𱢭","闊","篲","𦾈","聲","藉","穙","䕌","趨","縿","鮮","糝","䨣","謝","顃","儨","糜","雖","𡣍","㸃","翳","闇","𣋓","鴜","黚","𦾓","龜","𫊣","黊","簋","縮","戴","𧪟","磻","醟","擧","𦌔","賷","𥂰","齋","霝","鮝","𪟺","貘","歜","聯","𥊽","𥪴","罽","谿","騀","磿","𨵩","蟄","𦼫","馘","篻","䳒","簒","毚","𥻿","聴","翼","磴","謟","鞞","皤","鍳","鞠","襄","縷","𩄎","𣫍","𫉬","𧷏","賸","𠮎","隸","皼","濟","𦒋","孺","濬","罅","薲","闋","𢖍","矯","虧","彌","赢","縵","㷿","謇","縻","嶽","鴹","臂"],"18":["𡗉","覆","翻","穫","題","𭋷","𡴪","𩄣","𥢺","顏","豐","𩷦","観","竄","雞","瀐","禰","擸","𡫟","鞫","繭","礕","𡂨","𨟍","䮕","鼀","闗","虩","𨪈","𨶒","𢇕","𩠬","𩄲","竅","鎮","璧","罈","擥","職","額","曛","𫎬","簟","𩈳","𨽡","䫕","簛","燾","蹔","髜","馥","𩣷","𡒲","瀉","鏌","鵙","𤐫","霧","檽","甖","饁","鬵","繒","𧑿","懵","瞿","𧫦","嚣","謹","轉","馤","𤣂","𣃍","𪤯","斷","𬞼","檻","𱤺","謾","䬕","蟮","𮒛","鎫","軀","蠆","繘","𩔊","聶","龎","𮧡","𣫖","𥳑","䌛","鵣","騐","𥜘","䏈","鎼","鵓","㩥","䑂","𧇽","顒","鬩","𠨧","邊","闓","歸","嚚","韞","蹙","鵝","簡","𮒣","鎣","彝","𨘢","黠","竆","璹","鎔","藥","𪋁","藴","羴","𮠾","獵","鵢","𭮧","闖","𥼚","釐","擾","壘","翹","齕","藜","繢","雝","𩔇","䕙","燹","巂","𠖥","騎","繞","𢐴","𭔟","𦪝","藝","鞮","䭉","臍","旛","闐","麏","𲇖","雙","擺","叢","闔","簞","藟","織","礜","𩘚","鯀","麌","𦗟","闒","儵","𰌱","闕","𢋨","離","𣄣","𪊿","蹢","簪","顔","𡾃","繠","襟","奰","䊩","醫","霤","藚","𣍓","藪","𩰿","𬙩","蟲","䢯","䇔","㬥","𦾴","雜","𣀔","𪘂","𫲓","瓊","𩡐","𣞈","𨤝","𡫥","𦔡","𢐷","繙","爀"],"19":["鏡","羶","顚","轎","蹵","𩸥","䕟","蟺","𧈅","蘇","疆","艶","孽","爂","𥽂","蘊","蟸","羸","覇","㰆","繩","龐","穩","𣞤","繴","蘋","𡃫","類","瀖","䳡","蘄","䠣","壞","贊","攀","䕥","瀕","𤔿","䩻","曡","羹","𤳯","𢸦","簾","瀧","簳","𫿞","鵪","顙","羅","𥨪","𩸮","𮢶","䝐","寳","懷","糪","願","嚩","鏄","聼","䚬","麓","簿","𫤼","臘","龏","嚬","韻","繰","覈","贇","𧁙","鵭","𢖙","騜","闞","璽","繫","𡄉","旟","辭","難","鏢","蘆","𫠙","贈","𩅜","鏖","𨶪","𪂣","瀨","韲","夒","𧀣","𮪍","臋","瀝","疇","簷","匶","懶","霪","鏨","爕","𩔪","㶋","櫐","𧸇","𥣞","譖","羆","蠃","爊","麗","𢋱","䉞","𢸧","𰥇","獺","靡","𮆘","𥃆","𤛿","𦆕","簫","㞡","勸","簽","鬊","嚴","𧀨","顛","寵","繯","䜌","鶂","𰘾","關","䊪","䨮","麕","𩔜","翽","廬","嬾","𧬉","櫓","𩌌","犢","藶","䞈","藺","警","識","鯨","醮","鼄","櫟"],"21":["灄","鶯","權","儼","䵯","鑁","懼","覽","𧃰","卛","䵗","蠢","辯","𪉷","䦲","歡","巋","籐","齧","𩐐","露","鷄","𩕘","𩰥","𩺃","曩","罍","𨷈","𠙳","驃","鷊","𨷖","闢","鶴","轟","籖","𧭛","躎","躑","鬘","𲌥","顥","竈","霸","禴","𬮔","纍","囂","鐸","鑊","贑","纈","屬","𦇏","赣","𪋘","嚻","𥽘","镾","夔","髓","𢑆","蠡","騾","𩕍","𰪠","羼","𠮓","攝","廱","𩮴","譶","竉","贔","𧲏","鐵","𧞻","𡈹","鐻","鰥"],"22":["攞","讃","𤴁","讀","𪅆","𩁘","籠","𣠵","囉","巒","轡","𩆞","龝","䕺","囊","鑍","糴","𩆖","𱋁","䜟","齪","𩦛","懿","霽","𰥉","鷟","穰","𪅀","𩺯","驕","𡿏","彎","鑒","孌","聽","邏","亹","灑","𪅝","欎","𩺰","聾","𩱕","蘿","巖","𬯵","龕","鷒","蘸","𪄿","體","覿","䲆","鱉","疊"],"25":["覊","黵","𪇠","臠","欝","廳","籮","蠻","𣡥"],"23":["蠱","變","黴","𧰟","𤓉","𱪘","讎","躘","𧥑","顯","籥","纖","𪘨","籣","籤","蠲","鷸","壨","𩕺","鱗","𣡈","䶞","𧄼","𭨒","讐","欒","𧅌","㸐","𩴶","齏","戀","驛","攣"],"24":["鹽","鼈","讒","鷹","顰","𧅚","靈","觀","靂","釀","靃","𦉥","黌","𣡍","𮭘","羈","蠶","贛","鬭","𡚤","雥","鑫","爤","𣡗","矕","𩼃","衢","𠓗","鱣","艷","𡚣"],"28":["钁","𱌦","𰙉","豔"],"29":["鬱"],"26":["驢","𪇼","𱬲","釁","𠑲","龥","䕿","飌"],"32":["龖","𤴐"],"30":["驫","鸞","𪙹","爨"],"27":["灥","𠨋","鑾","豓","纜"],"33":["麤"],"31":["𧟛"]}